{
  "generatedBy": "S1APICoverageAnalyzer",
  "version": "1.0",
  "entries": [
    {
      "timestamp": "2026-01-19T00:40:42.7588948Z",
      "classCoveragePercentage": 27.938144329896907,
      "memberCoveragePercentage": 0,
      "totalClasses": 970,
      "coveredClasses": 271,
      "totalMembers": 24717,
      "coveredMembers": 0,
      "excludedClasses": 1054,
      "gameAssemblyVersion": "0.0.0.0",
      "gameAssemblyHash": "B9A1838C5D2667C2FD3CB8E43F8E5F8E9412FD63C771E2000C5B8D635DB42D16",
      "analyzerVersion": "1.0.0.0",
      "events": [],
      "note": null
    },
    {
      "timestamp": "2026-01-22T21:47:33.752527Z",
      "classCoveragePercentage": 27.938144329896907,
      "memberCoveragePercentage": 0,
      "totalClasses": 970,
      "coveredClasses": 271,
      "totalMembers": 24717,
      "coveredMembers": 0,
      "excludedClasses": 1054,
      "gameAssemblyVersion": "0.0.0.0",
      "gameAssemblyHash": "B9A1838C5D2667C2FD3CB8E43F8E5F8E9412FD63C771E2000C5B8D635DB42D16",
      "analyzerVersion": "1.0.0.0",
      "events": [],
      "note": null
    },
    {
      "timestamp": "2026-01-23T00:02:40.4474636Z",
      "classCoveragePercentage": 27.938144329896907,
      "memberCoveragePercentage": 0,
      "totalClasses": 970,
      "coveredClasses": 271,
      "totalMembers": 24717,
      "coveredMembers": 0,
      "excludedClasses": 1054,
      "gameAssemblyVersion": "0.0.0.0",
      "gameAssemblyHash": "B9A1838C5D2667C2FD3CB8E43F8E5F8E9412FD63C771E2000C5B8D635DB42D16",
      "analyzerVersion": "1.0.0.0",
      "events": [],
      "note": null
    }
  ],
  "latestEntry": {
    "timestamp": "2026-01-23T00:02:40.4474636Z",
    "classCoveragePercentage": 27.938144329896907,
    "memberCoveragePercentage": 0,
    "totalClasses": 970,
    "coveredClasses": 271,
    "totalMembers": 24717,
    "coveredMembers": 0,
    "excludedClasses": 1054,
    "gameAssemblyVersion": "0.0.0.0",
    "gameAssemblyHash": "B9A1838C5D2667C2FD3CB8E43F8E5F8E9412FD63C771E2000C5B8D635DB42D16",
    "analyzerVersion": "1.0.0.0",
    "events": [],
    "note": null
  }
}